{
    "chats": {
        "2000000012": {
            "manlix_id": 1,
            "title": "Основная Беседа",
            "---info---": "Ниже список персонала для этой беседы",
            "staff": {
                "870757778": [
                    "Владелец",
                    "MANLIX MANAGER"
                ]
            }
        },
        "2000000015": {
            "title": "Porno с MANLIX MAANGER",
            "staff": {},
            "mutes": {},
            "stats": {
                "870757778": {
                    "count": 7,
                    "last": 1772819382.663786
                }
            }
        },
        "2000000004": {
            "title": "Чат 2000000004",
            "staff": {
                "870757778": [
                    "Владелец",
                    "Misha Manlix"
                ],
                "478437927": [
                    "Спец. Администратор",
                    "Администрации"
                ]
            },
            "mutes": {},
            "stats": {
                "870757778": {
                    "count": 20,
                    "last": 1772812182.276304
                }
            }
        },
        "2000000017": {
            "title": "Чат 2000000017",
            "staff": {},
            "mutes": {},
            "stats": {
                "870757778": {
                    "count": 3,
                    "last": 1772827751.045669
                }
            },
            "type": "def"
        }
    },
    "gstaff": {
        "spec": 870757778,
        "main_zam": null,
        "zams": []
    }
}